[
  {
    "Texte": "Soul Eater",
    "Url Thumb": "https://files.catbox.moe/qv17ap.jpg",
    "Catégorie": "anime",
    "Bio": "",
    "Info": "",
    "Saisons": [
      {
        "description": "Soul Eater raconte l'histoire de 3 jeunes apprentis faucheurs d'âmes, de l'école Shibusen, où ils apprennent à devenir de vrais faucheurs d'âmes confirmés. Ces jeunes gens possèdent des armes humaines pouvant prendre l'apparence d'armes diverses, appelées "armes démoniaques". En leur faisant manger 99 âmes d'humains corrompus (Oeufs du grand Dévoreur) et 1 âme de sorcière, ils les transformeront en Death Scythe, des armes démoniaques plus puissantes et plus évoluées. Tout serait bien si c'était aussi simple, malheureusement de nombreux obstacles barrent la route des protagonistes.",
        "bio": " ソウルイーター",
        "info": ":Action - Aventure - Comédie - Drame - Fantasy - Surnaturel",
        "episodes": [
          { "description": "", "video": "" },
          { "description": "", "video": "" },
          { "description": "", "video": "" },
          { "description": "", "video": "" },
          { "description": "", "video": "" },
          { "description": "", "video": "" },
          { "description": "", "video": "" },
          { "description": "", "video": "" },
          { "description": "", "video": "" },
          { "description": "", "video": "" },
          { "description": "", "video": "" },
          { "description": "", "video": "" }
        ]
      },
      {
        "description": "",
        "bio": "",
        "info": "",
        "episodes": [
          { "description": "", "video": "" },
          { "description": "", "video": "" },
          { "description": "", "video": "" },
          { "description": "", "video": "" },
          { "description": "", "video": "" },
          { "description": "", "video": "" },
          { "description": "", "video": "" },
          { "description": "", "video": "" },
          { "description": "", "video": "" },
          { "description": "", "video": "" },
          { "description": "", "video": "" },
          { "description": "", "video": "" }
        ]
      }
    ]
  }
]
