[
  {
    "Titre": "Dragons",
    "Url Thumb": "https://res.cloudinary.com/dckwrqrur/image/upload/v1755032119/tf-stream-url/IMG_20250812_165215_974_ekngn0.jpg",
    "Catégorie": "film", 
    "Saisons": [
      {
        "description": "Sur la rude île de Berk, où les Vikings et les dragons sont des ennemis jurés depuis des générations, Harold se distingue. Fils inventif, mais négligé du chef Stoïck la brute, Harold défie des siècles de tradition en se liant d'amitié avec le dragon Krokmou, une Furie Nocturne.",
        "bio": "Le Furie Nocturne",
        "info": "Âge conseillé 6+",
        "episodes": [
          {
            "description": "Je vous conseille d'appuyer sur un épisode pour que ça puisse charger",
            "video": "https://archive.org/download/tf-stream-film-ziam_20250812/-%20Dragons%20%282025%29.mp4"
          }
        ]
      }
    ]
  }
]
